better_venv_killer-1.0.0.dist-info/licenses/LICENSE
venv_killer/__init__.py
venv_killer/cli.py
venv_killer/core.py
venv_killer/gui.py
better_venv_killer-1.0.0.dist-info/METADATA
better_venv_killer-1.0.0.dist-info/WHEEL
better_venv_killer-1.0.0.dist-info/entry_points.txt
better_venv_killer-1.0.0.dist-info/top_level.txt
better_venv_killer-1.0.0.dist-info/RECORD
