Metadata-Version: 2.4
Name: better-venv-killer
Version: 1.0.0
Summary: Find and delete Python virtual environments to free disk space
Home-page: https://github.com/darkbits018
Author: holygrimmdev
Author-email: Your Name <your.email@example.com>
License: MIT
Project-URL: Homepage, https://github.com/darkbits018/better-venv-killer
Project-URL: Bug Reports, https://github.com/darkbits018/better-venv-killer/issues
Project-URL: Source, https://github.com/darkbits018/better-venv-killer
Keywords: virtual environment,venv,conda,cleanup,disk space,developer tools
Classifier: Development Status :: 5 - Production/Stable
Classifier: Intended Audience :: Developers
Classifier: Topic :: Software Development :: Build Tools
Classifier: License :: OSI Approved :: MIT License
Classifier: Programming Language :: Python :: 3
Classifier: Programming Language :: Python :: 3.7
Classifier: Programming Language :: Python :: 3.8
Classifier: Programming Language :: Python :: 3.9
Classifier: Programming Language :: Python :: 3.10
Classifier: Programming Language :: Python :: 3.11
Classifier: Programming Language :: Python :: 3.12
Classifier: Operating System :: OS Independent
Classifier: Environment :: Console
Classifier: Environment :: X11 Applications
Requires-Python: >=3.7
License-File: LICENSE
Provides-Extra: dev
Requires-Dist: pytest>=6.0; extra == "dev"
Requires-Dist: black; extra == "dev"
Requires-Dist: flake8; extra == "dev"
Dynamic: author
Dynamic: home-page
Dynamic: license-file
Dynamic: requires-python
